datatypes/__init__.py
datatypes/base_datatype.py
datatypes/builtin_datatype.py
grammar/__init__.py
hhat_lang/__init__.py
hhat_lang/__main__.py
hhat_lang/example.py
hhat_lang/exec.py
hhat_lang/hhat_ast.py
hhat_lang/hhat_pre_eval.py
hhat_lang/version.txt
hhat_lang/datatypes/__init__.py
hhat_lang/datatypes/base_datatype.py
hhat_lang/datatypes/builtin_datatype.py
hhat_lang/grammar/__init__.py
hhat_lang/interpreter/__init__.py
hhat_lang/interpreter/eval.py
hhat_lang/interpreter/memory.py
hhat_lang/interpreter/parsing.py
hhat_lang/interpreter/semantics.py
hhat_lang/interpreter/builtins/__init__.py
hhat_lang/interpreter/builtins/builtin_fn.py
hhat_lang/syntax_trees/__init__.py
hhat_lang/syntax_trees/ast.py
hhat_lang/syntax_trees/literal_define.py
hhat_lang/utils/__init__.py
hhat_lang/utils/utils.py
hhat_lang-0.1.0a7.data/data/version/version.txt
interpreter/__init__.py
interpreter/eval.py
interpreter/memory.py
interpreter/parsing.py
interpreter/semantics.py
interpreter/builtins/__init__.py
interpreter/builtins/builtin_fn.py
syntax_trees/__init__.py
syntax_trees/ast.py
syntax_trees/literal_define.py
utils/__init__.py
utils/utils.py
hhat_lang-0.1.0a7.dist-info/LICENSE.txt
hhat_lang-0.1.0a7.dist-info/METADATA
hhat_lang-0.1.0a7.dist-info/WHEEL
hhat_lang-0.1.0a7.dist-info/entry_points.txt
hhat_lang-0.1.0a7.dist-info/top_level.txt
hhat_lang-0.1.0a7.dist-info/RECORD
